tests/__init__.py
tests/test_repository.py
student_manager-0.1.1.dist-info/METADATA
student_manager-0.1.1.dist-info/WHEEL
student_manager-0.1.1.dist-info/entry_points.txt
student_manager-0.1.1.dist-info/top_level.txt
student_manager-0.1.1.dist-info/RECORD
