Metadata-Version: 2.4
Name: student-manager
Version: 0.1.1
Summary: A simple student manager program
Author: lyh
Author-email: 1521847437@qq.com
License: MIT
Keywords: student manager
Classifier: Programming Language :: Python :: 3
Classifier: License :: OSI Approved :: MIT License
Classifier: Operating System :: OS Independent
Requires-Python: >=3.6
Dynamic: author
Dynamic: author-email
Dynamic: classifier
Dynamic: description
Dynamic: description-content-type
Dynamic: keywords
Dynamic: license
Dynamic: requires-python
Dynamic: summary
